sphinxfortran_ng/__init__.py
sphinxfortran_ng/crackfortran_for_sphinx.py
sphinxfortran_ng/fortran_autodoc.py
sphinxfortran_ng/fortran_domain.py
sphinxfortran_ng-0.5.5.dist-info/licenses/LICENSE
sphinxfortran_ng-0.5.5.dist-info/METADATA
sphinxfortran_ng-0.5.5.dist-info/WHEEL
sphinxfortran_ng-0.5.5.dist-info/top_level.txt
sphinxfortran_ng-0.5.5.dist-info/RECORD
