Metadata-Version: 2.4
Name: sphinxfortran_ng
Version: 0.5.5
Summary: An improved version of the sphinx-fortran python module
Author-email: Lorenzo Crippa <crippa.lorenzo@gmail.com>
Project-URL: Repository, https://github.com/SciFortran/sphinxfortran_ng
Classifier: Programming Language :: Python :: 3
Classifier: License :: OSI Approved :: MIT License
Classifier: Operating System :: OS Independent
Requires-Python: >=3.8
License-File: LICENSE
Dynamic: license-file
